{
	"ImportPath": "github.com/safaaleigh/api-template",
	"GoVersion": "go1.8",
	"GodepVersion": "v79",
	"Deps": [
		{
			"ImportPath": "github.com/BurntSushi/toml",
			"Comment": "v0.3.0-7-ga368813",
			"Rev": "a368813c5e648fee92e5f6c30e3944ff9d5e8895"
		},
		{
			"ImportPath": "github.com/Sirupsen/logrus",
			"Comment": "1.0.2-6-ge49c59d",
			"Rev": "e49c59d69b89746796d48156991108c80faf1d7d"
		},
		{
			"ImportPath": "github.com/asaskevich/govalidator",
			"Comment": "v6-20-gaa5cce4",
			"Rev": "aa5cce4a76edb1a5acecab1870c17abbffb5419e"
		},
		{
			"ImportPath": "github.com/google/uuid",
			"Comment": "0.2-5-g1c6adf5",
			"Rev": "1c6adf5cd133db09196c44ffae1f77ebf4da64aa"
		},
		{
			"ImportPath": "github.com/jmoiron/sqlx",
			"Comment": "sqlx-v1.1-123-gd9bd385",
			"Rev": "d9bd385d68c068f1fabb5057e3dedcbcbb039d0f"
		},
		{
			"ImportPath": "github.com/jmoiron/sqlx/reflectx",
			"Comment": "sqlx-v1.1-123-gd9bd385",
			"Rev": "d9bd385d68c068f1fabb5057e3dedcbcbb039d0f"
		},
		{
			"ImportPath": "github.com/klauspost/compress/flate",
			"Comment": "v1.2.1-8-gf3dce52",
			"Rev": "f3dce52e0576655d55fd69e74b63da96ad1108f3"
		},
		{
			"ImportPath": "github.com/klauspost/compress/gzip",
			"Comment": "v1.2.1-8-gf3dce52",
			"Rev": "f3dce52e0576655d55fd69e74b63da96ad1108f3"
		},
		{
			"ImportPath": "github.com/klauspost/compress/zlib",
			"Comment": "v1.2.1-8-gf3dce52",
			"Rev": "f3dce52e0576655d55fd69e74b63da96ad1108f3"
		},
		{
			"ImportPath": "github.com/klauspost/cpuid",
			"Comment": "v1.0",
			"Rev": "09cded8978dc9e80714c4d85b0322337b0a1e5e0"
		},
		{
			"ImportPath": "github.com/lib/pq",
			"Comment": "go1.0-cutoff-173-gdd1fe20",
			"Rev": "dd1fe2071026ce53f36a39112e645b4d4f5793a4"
		},
		{
			"ImportPath": "github.com/lib/pq/oid",
			"Comment": "go1.0-cutoff-173-gdd1fe20",
			"Rev": "dd1fe2071026ce53f36a39112e645b4d4f5793a4"
		},
		{
			"ImportPath": "github.com/valyala/bytebufferpool",
			"Rev": "e746df99fe4a3986f4d4f79e13c1e0117ce9c2f7"
		},
		{
			"ImportPath": "github.com/valyala/fasthttp",
			"Comment": "v20160617-111-g52a0993",
			"Rev": "52a0993b96f032dea57fa93081d7c0a1aa906430"
		},
		{
			"ImportPath": "github.com/valyala/fasthttp/fasthttputil",
			"Comment": "v20160617-111-g52a0993",
			"Rev": "52a0993b96f032dea57fa93081d7c0a1aa906430"
		},
		{
			"ImportPath": "github.com/valyala/fasthttp/stackless",
			"Comment": "v20160617-111-g52a0993",
			"Rev": "52a0993b96f032dea57fa93081d7c0a1aa906430"
		},
		{
			"ImportPath": "github.com/valyala/fasthttprouter",
			"Comment": "v1.1-29-g24073dd",
			"Rev": "24073dd8f323cb52fe24f2f51bda5e6b1c2a0f18"
		},
		{
			"ImportPath": "golang.org/x/sys/unix",
			"Rev": "abf9c25f54453410d0c6668e519582a9e1115027"
		}
	]
}
